verilog_codes/Jhonson_Ring _counter/DFF.v
module DFF (
    output reg Q, 
    input D, clk, rst
);

always @(negedge clk ) Q<=D;
always @(negedge rst) Q<=1'b1;

endmodule

verilog_codes/Jhonson_Ring _counter/counter.v
`include "DFF.v"
module counter (
    output Q0, Q1,Q2,Q3,
    input D0, D1, D2, D3,
    input clk,rst
);

DFF Q_3(Q3, ((!D1)&&D0)+((!D0)&&D1), clk, rst); 
DFF Q_2(Q2, D3, clk, rst); 
DFF Q_1(Q1, D2, clk, rst); 
DFF Q_0(Q0, D1, clk, rst); 
endmodule

verilog_codes/Jhonson_Ring _counter/counter_tb.v
//test bench for d flip flop
//1. Declare module and ports
`timescale 1ns/1ns
`include "counter.v"

module counter_tb;
reg A,B,C,D,clk,rst;
wire A2,B2,C2,D2;
counter DUT(D2, C2, B2, A2, D, C, B, A, clk, rst); 

initial begin
    $dumpfile("counter_tb.vcd");
    $dumpvars(0,counter_tb);
    clk=1;
    forever #5 clk=~clk;
end


initial 
    begin 
        $dumpfile("counter_tb.vcd");
        $dumpvars(0,counter_tb);
        #2 rst=0;
        #1 rst=1;
        #1 rst=0;
        #10 A=0; B=0; C=0; D=1;
        repeat(60)begin
            #5.05 A=A2; B=B2; C=C2; D=D2;
        end            
        $finish;

    end 
endmodule

verilog_codes/Jhonson_Ring _counter/counter_tb.vcd
$date
	Mon May 17 20:29:44 2021
$end
$version
	Icarus Verilog
$end
$timescale
	1ns
$end
$scope module counter_tb $end
$var wire 1 ! D2 $end
$var wire 1 " C2 $end
$var wire 1 # B2 $end
$var wire 1 $ A2 $end
$var reg 1 % A $end
$var reg 1 & B $end
$var reg 1 ' C $end
$var reg 1 ( D $end
$var reg 1 ) clk $end
$var reg 1 * rst $end
$scope module DUT $end
$var wire 1 ( D0 $end
$var wire 1 ' D1 $end
$var wire 1 & D2 $end
$var wire 1 % D3 $end
$var wire 1 ) clk $end
$var wire 1 * rst $end
$var wire 1 $ Q3 $end
$var wire 1 # Q2 $end
$var wire 1 " Q1 $end
$var wire 1 ! Q0 $end
$scope module Q_0 $end
$var wire 1 ' D $end
$var wire 1 ) clk $end
$var wire 1 * rst $end
$var reg 1 ! Q $end
$upscope $end
$scope module Q_1 $end
$var wire 1 & D $end
$var wire 1 ) clk $end
$var wire 1 * rst $end
$var reg 1 " Q $end
$upscope $end
$scope module Q_2 $end
$var wire 1 % D $end
$var wire 1 ) clk $end
$var wire 1 * rst $end
$var reg 1 # Q $end
$upscope $end
$scope module Q_3 $end
$var wire 1 + D $end
$var wire 1 ) clk $end
$var wire 1 * rst $end
$var reg 1 $ Q $end
$upscope $end
$upscope $end
$upscope $end
$scope module counter_tb $end
$scope module DUT $end
$scope module Q_0 $end
$upscope $end
$scope module Q_1 $end
$upscope $end
$scope module Q_2 $end
$upscope $end
$scope module Q_3 $end
$upscope $end
$upscope $end
$upscope $end
$enddefinitions $end
#0
$dumpvars
x+
x*
1)
x(
x'
x&
x%
x$
x#
x"
x!
$end
#2
1$
1#
1"
1!
0*
#3
1*
#4
0*
#5
x$
x#
x"
x!
0)
#10
1)
#14
1+
1(
0'
0&
0%
#15
0!
0"
0#
1$
0)
#19
0+
0(
1%
#20
1)
#25
0$
1#
0)
#29
1&
0%
#30
1)
#35
1"
0#
0)
#39
1+
1'
0&
#40
1)
#45
1$
0"
1!
0)
#49
1+
1(
0'
1%
#50
1)
#55
0!
1#
0)
#59
0+
0(
1&
#60
1)
#65
0$
1"
0)
#69
1+
1'
0%
#70
1)
#75
1!
0#
1$
0)
#79
0+
1(
0&
1%
#80
1)
#85
0$
1#
0"
0)
#89
1+
0'
1&
0%
#90
1)
#95
0!
1"
0#
1$
0)
#99
1+
0(
1'
0&
1%
#100
1)
#105
1#
0"
1!
0)
#109
1+
1(
0'
1&
#110
1)
#115
0!
1"
0)
#119
1+
0(
1'
#120
1)
#125
1!
0)
#129
0+
1(
#130
1)
#135
0$
0)
#139
0%
#140
1)
#145
0#
0)
#149
0&
#150
1)
#155
0"
0)
#159
1+
0'
#160
1)
#165
1$
0!
0)
#169
0+
0(
1%
#170
1)
#175
1#
0$
0)
#179
1&
0%
#180
1)
#185
0#
1"
0)
#189
1+
1'
0&
#190
1)
#195
1!
0"
1$
0)
#199
1+
1(
0'
1%
#200
1)
#205
1#
0!
0)
#209
0+
0(
1&
#210
1)
#215
1"
0$
0)
#219
1+
1'
0%
#220
1)
#225
1$
0#
1!
0)
#229
0+
1(
0&
1%
#230
1)
#235
0"
1#
0$
0)
#239
1+
0'
1&
0%
#240
1)
#245
1$
0#
1"
0!
0)
#249
1+
0(
1'
0&
1%
#250
1)
#255
1!
0"
1#
0)
#259
1+
1(
0'
1&
#260
1)
#265
1"
0!
0)
#269
1+
0(
1'
#270
1)
#275
1!
0)
#279
0+
1(
#280
1)
#285
0$
0)
#289
0%
#290
1)
#295
0#
0)
#299
0&
#300
1)
#305
0"
0)
#309
1+
0'
