verilog_codes/Jhonson_Ring _counter/DFF.v
module DFF (
    output reg Q, 
    input D, clk, rst
);

always @(negedge clk ) Q<=D;
always @(negedge rst) Q<=1'b1;

endmodule

verilog_codes/Jhonson_Ring _counter/DFF_tb.v

`include "DFF.v"
module DFF_tb;
wire Q;
reg D,clk,rst;

DFF dut(Q,D,clk,rst);
initial #200 $finish;

initial begin
    $dumpfile("DFF_tb.vcd");
    $dumpvars(0,DFF_tb);
    clk=1;
    forever #5 clk=~clk;
end

initial fork
    #2 rst=0;
    #3 rst=1;
    #4 rst=0;
    #10 D=0;
    #20 D=1;
    #40 D=0;
    #52 D=1;
    #68 D=0;
    #89 D=1;
    #114 D=0;
    
join 
    
endmodule

verilog_codes/Jhonson_Ring _counter/DFF_tb.vcd
$date
	Mon May 17 01:41:56 2021
$end
$version
	Icarus Verilog
$end
$timescale
	1s
$end
$scope module DFF_tb $end
$var wire 1 ! Q $end
$var reg 1 " D $end
$var reg 1 # clk $end
$var reg 1 $ rst $end
$scope module dut $end
$var wire 1 " D $end
$var wire 1 # clk $end
$var wire 1 $ rst $end
$var reg 1 ! Q $end
$upscope $end
$upscope $end
$enddefinitions $end
#0
$dumpvars
x$
0#
x"
x!
$end
#2
0!
0$
#3
1$
#4
0$
#5
1#
#10
0#
0"
#15
1#
#20
1!
0#
1"
#25
1#
#30
0#
#35
1#
#40
0!
0#
0"
#45
1#
#50
0#
#52
1"
#55
1#
#60
1!
0#
#65
1#
#68
0"
#70
0!
0#
#75
1#
#80
0#
#85
1#
#89
1"
#90
1!
0#
#95
1#
#100
0#
#105
1#
#110
0#
#114
0"
#115
1#
#120
0!
0#
