verilog_codes/Sequence_Generator/DFF.v
module DFF (
    output reg Q, 
    input D, clk, rst
);

always @(posedge clk ) Q<=D;
always @(negedge rst) Q<=1'b0;

endmodule

verilog_codes/Sequence_Generator/Gen.v
`include "DFF.v"
module Gen (
    output Q2, Q1, Q0, Y,
    input S2, S1, S0, X_i, clk,rst
);

DFF Q_2(Q2, (S2 && (!S1)) || (S1 && S0) , clk, rst); 

DFF Q_1(Q1, ( ((!S1) && S0) || ((!S2) && S1 && (!S0)) ), clk, rst); 

DFF Q_0(Q0, ((!S0 && X_i) || ((!S2) && S1 && (!S0)) || ((S2 && (!S1)) && (!S0))), clk, rst); 

assign Y= S0 || ((!S2) && (!S1) && X_i) || (S2 && S1 && X_i);

    
endmodule

verilog_codes/Sequence_Generator/Gen_tb.v
`timescale 1ns/1ns
`include "Gen.v"

module Gen_tb;
reg S2, S1, S0, X_i,clk,rst;
wire Q2, Q1, Q0, Y;
Gen DUT(Q2, Q1, Q0, Y, S2, S1, S0, X_i, clk, rst); 

initial begin
    $dumpfile("Gen_tb.vcd");
    $dumpvars(0, Gen_tb);
    clk=0;
    forever #5 clk=~clk;
end


initial 
    begin 
        $dumpfile("Gen_tb.vcd");
        $dumpvars(0,Gen_tb);
        #2 rst=0;
        #1 rst=1;
        #1 rst=0;
        #10 S2=0; S1=0; S0=0; X_i=1;
        repeat(2)begin
            #5.05 S2=Q2; S1=Q1; S0=Q0;
        end   
        X_i=0;
        repeat(2)begin
            #5.05 S2=Q2; S1=Q1; S0=Q0;
        end 
        X_i=1;
        repeat(2)begin
            #5.05 S2=Q2; S1=Q1; S0=Q0;
        end 
        X_i=0;
        repeat(6)begin
            #5.05 S2=Q2; S1=Q1; S0=Q0;
        end 
        X_i=1;
        repeat(20)begin
            #5.05 S2=Q2; S1=Q1; S0=Q0;
        end 
        X_i=0;
        repeat(10) begin
            #5.05 S2=Q2; S1=Q1; S0=Q0;
        end

        repeat(2)begin
            #5.05 S2=Q2; S1=Q1; S0=Q0;
        end   
        X_i=0;
        repeat(2)begin
            #5.05 S2=Q2; S1=Q1; S0=Q0;
        end 
        X_i=1;
        repeat(2)begin
            #5.05 S2=Q2; S1=Q1; S0=Q0;
        end 
        X_i=0;
        repeat(6)begin
            #5.05 S2=Q2; S1=Q1; S0=Q0;
        end 
        X_i=1;
        repeat(20)begin
            #5.05 S2=Q2; S1=Q1; S0=Q0;
        end 
        
        $finish;

    end 
endmodule

verilog_codes/Sequence_Generator/Gen_tb.vcd
$date
	Mon May 17 16:10:32 2021
$end
$version
	Icarus Verilog
$end
$timescale
	1ns
$end
$scope module Gen_tb $end
$var wire 1 ! Y $end
$var wire 1 " Q2 $end
$var wire 1 # Q1 $end
$var wire 1 $ Q0 $end
$var reg 1 % S0 $end
$var reg 1 & S1 $end
$var reg 1 ' S2 $end
$var reg 1 ( X_i $end
$var reg 1 ) clk $end
$var reg 1 * rst $end
$scope module DUT $end
$var wire 1 % S0 $end
$var wire 1 & S1 $end
$var wire 1 ' S2 $end
$var wire 1 ( X_i $end
$var wire 1 ! Y $end
$var wire 1 ) clk $end
$var wire 1 * rst $end
$var wire 1 " Q2 $end
$var wire 1 # Q1 $end
$var wire 1 $ Q0 $end
$scope module Q_0 $end
$var wire 1 + D $end
$var wire 1 ) clk $end
$var wire 1 * rst $end
$var reg 1 $ Q $end
$upscope $end
$scope module Q_1 $end
$var wire 1 , D $end
$var wire 1 ) clk $end
$var wire 1 * rst $end
$var reg 1 # Q $end
$upscope $end
$scope module Q_2 $end
$var wire 1 - D $end
$var wire 1 ) clk $end
$var wire 1 * rst $end
$var reg 1 " Q $end
$upscope $end
$upscope $end
$upscope $end
$scope module Gen_tb $end
$scope module DUT $end
$scope module Q_0 $end
$upscope $end
$scope module Q_1 $end
$upscope $end
$scope module Q_2 $end
$upscope $end
$upscope $end
$upscope $end
$enddefinitions $end
#0
$dumpvars
x-
x,
x+
x*
0)
x(
x'
x&
x%
x$
x#
x"
x!
$end
#2
0"
0#
0$
0*
#3
1*
#4
0*
#5
x"
x#
x$
1)
#10
0)
#14
1!
1+
0,
0-
1(
0%
0&
0'
#15
1$
0#
0"
1)
#19
0+
1,
1%
#20
0)
#24
0(
#25
1#
0$
1)
#29
1+
0!
0%
1&
#30
0)
#34
1(
#35
1$
1)
#39
0+
1-
1!
0,
1%
#40
0)
#44
0(
#45
1"
0#
0$
1)
#49
0!
1+
0%
0&
1'
#50
0)
#55
1$
1)
#59
1,
1!
0+
1%
#60
0)
#65
1#
0$
1)
#69
0!
0-
0,
0%
1&
#70
0)
#74
1+
1!
1(
#75
1$
0#
0"
1)
#79
0+
1,
1%
0&
0'
#80
0)
#85
1#
0$
1)
#89
0!
1+
0%
1&
#90
0)
#95
1$
1)
#99
0+
1-
1!
0,
1%
#100
0)
#105
1"
0#
0$
1)
#109
0!
1+
0%
0&
1'
#110
0)
#115
1$
1)
#119
0+
1,
1!
1%
#120
0)
#125
1#
0$
1)
#129
1+
0-
0,
0%
1&
#130
0)
#135
1$
0#
0"
1)
#139
0+
1,
1%
0&
0'
#140
0)
#145
1#
0$
1)
#149
0!
1+
0%
1&
#150
0)
#155
1$
1)
#159
0+
1-
1!
0,
1%
#160
0)
#165
1"
0#
0$
1)
#169
0!
1+
0%
0&
1'
#170
0)
#174
0(
#175
1$
1)
#179
1,
1!
0+
1%
#180
0)
#185
1#
0$
1)
#189
0!
0-
0,
0%
1&
#190
0)
#195
0#
0"
1)
#199
0&
0'
#200
0)
#205
1)
#210
0)
#215
1)
#220
0)
#225
1)
#230
0)
#235
1)
#240
0)
#244
1+
1!
1(
#245
1$
1)
#249
0+
1,
1%
#250
0)
#254
0(
#255
0$
1#
1)
#259
1+
0!
0%
1&
#260
0)
#265
1$
1)
#269
0+
1-
1!
0,
1%
#270
0)
#275
0$
0#
1"
1)
#279
0!
1+
0%
0&
1'
#280
0)
#284
1(
#285
1$
1)
#289
0+
1,
1!
1%
#290
0)
#295
0$
1#
1)
#299
1+
0-
0,
0%
1&
#300
0)
#305
0"
0#
1$
1)
#309
0+
1,
1%
0&
0'
#310
0)
#315
0$
1#
1)
#319
0!
1+
0%
1&
#320
0)
#325
1$
1)
#329
0+
1-
1!
0,
1%
#330
0)
#335
0$
0#
1"
1)
#339
0!
1+
0%
0&
1'
#340
0)
#345
1$
1)
#349
0+
1,
1!
1%
#350
0)
#355
0$
1#
1)
#359
1+
0-
0,
0%
1&
#360
0)
#365
0"
0#
1$
1)
#369
0+
1,
1%
0&
0'
#370
0)
#375
0$
1#
1)
#379
0!
1+
0%
1&
