verilog_codes/Gray_Code_Counter_SRFF/SR_Latch.v
module SR_Latch(S, R, clk,p,c ,Q ,Qb);
    input S,R,clk,p,c;
    output Q,Qb;
    wire sk,rk,x,y;
    nand g1(sk,clk,S);
    nand g2(rk,clk,R);
    assign Q= ~(Qb & ~p & sk);
    assign Qb=~(Q & ~c & rk);
endmodule

verilog_codes/Gray_Code_Counter_SRFF/SR_FlipFlop.v
`include "SR_Latch.v"

module SR_FlipFlop(S, R, clk, p, c, Q,Qb);
    input S, R, clk,p, c;
    output Q,Qb;
    wire a,b;
    SR_Latch S1(.S(S),.R(R),.clk(~clk),.p(p), .c(c), .Q(a),.Qb(b));
    SR_Latch S2(.S(a),.R(b),.clk(clk),.p(p), .c(c), .Q(Q),.Qb(Qb));
endmodule

verilog_codes/Gray_Code_Counter_SRFF/Mod_Counter.v
`include "SR_FlipFlop.v"

module Mod_Counter(A,B,C,D,clk,p,c, A2,B2,C2,D2);
    input A,B,C,D,clk,p,c;
    output A2,B2,C2,D2;
    wire a2,b2,c2,d2;
    wire sa,ra,sb,rb,sc,rc,sd,rd;
    assign sa=B && !C && !D;
    assign ra=!B && !C && !D;
    assign sb=!A && C && !D;
    assign rb= A && C && !D;
    assign sc=(!A && !B && D) || (A && B && D);
    assign rc=(!A && B && D) || (A && !B && D);
    assign sd=(!A && !B && !C) || (A && B && !C) || (!A && B && C) || (A && !B && C);
    assign rd=(!A && !B && C) || (A && B && C) || (!A && B && !C) || (A && !B && !C);
    SR_FlipFlop S1(.S(sa),.R(ra),.clk(clk),.p(p), .c(c), .Q(A2),.Qb(a2));
    SR_FlipFlop S2(.S(sb),.R(rb),.clk(clk),.p(p), .c(c),.Q(B2),.Qb(b2));
    SR_FlipFlop S3(.S(sc),.R(rc),.clk(clk),.p(p), .c(c),.Q(C2),.Qb(c2));
    SR_FlipFlop S4(.S(sd),.R(rd),.clk(clk),.p(p), .c(c),.Q(D2),.Qb(d2));
endmodule



 /*wire q1,q2;
    and(q1,C,D);
    and(q2,q1,B);
    and(sa,~A,q2);
    and(ra,A,q2);
    and(sb,~B,q1);
    and(rb,B,q1);
    and(sc,D,1);
    and(rc,~D,1);
    and(sd,~D,1);
    and(rd,D,1);*/

verilog_codes/Gray_Code_Counter_SRFF/Mod_Counter_tb.v
//test bench for d flip flop
//1. Declare module and ports
`timescale 1ns/1ns
`include "Mod_Counter.v"

module Mod_Counter_tb;
reg A,B,C,D,clk,p,c;
wire A2,B2,C2,D2;

//2. Instantiate the module we want to test. We have instantiated the srff_behavior
Mod_Counter DUT(.A(A), .B(B), .C(C), .D(D), .clk(clk),.p(p), .c(c), .A2(A2), .B2(B2), .C2(C2), .D2(D2)); // instantiation by port name.

//3. Monitor TB ports
//$monitor("simtime = %g, CLK = %b, S = %b, R = %b, Q = %b, QBAR = %b", $time, CLK, S, R, Q, QBAR);

//4. apply test vectors

initial 
    begin 
        $dumpfile("Mod_Counter_tb.vcd");
        $dumpvars(0,Mod_Counter_tb);
        clk=0; p=0; c=1;
        A=0; B=0; C=0; D=0;
        #1; p=0;c=0;
        repeat(100)begin
            A=A2; B=B2; C=C2; D=D2; #5.05;
        end
            
        $finish;
    end 
    always 
        #5 clk=~clk; 
    
endmodule

verilog_codes/Gray_Code_Counter_SRFF/Mod_Counter_tb.vcd
$date
	Tue May 18 06:44:09 2021
$end
$version
	Icarus Verilog
$end
$timescale
	1ns
$end
$scope module Mod_Counter_tb $end
$var wire 1 ! D2 $end
$var wire 1 " C2 $end
$var wire 1 # B2 $end
$var wire 1 $ A2 $end
$var reg 1 % A $end
$var reg 1 & B $end
$var reg 1 ' C $end
$var reg 1 ( D $end
$var reg 1 ) c $end
$var reg 1 * clk $end
$var reg 1 + p $end
$scope module DUT $end
$var wire 1 % A $end
$var wire 1 & B $end
$var wire 1 ' C $end
$var wire 1 ( D $end
$var wire 1 ) c $end
$var wire 1 * clk $end
$var wire 1 + p $end
$var wire 1 , ra $end
$var wire 1 - rb $end
$var wire 1 . rc $end
$var wire 1 / rd $end
$var wire 1 0 sa $end
$var wire 1 1 sb $end
$var wire 1 2 sc $end
$var wire 1 3 sd $end
$var wire 1 4 d2 $end
$var wire 1 5 c2 $end
$var wire 1 6 b2 $end
$var wire 1 7 a2 $end
$var wire 1 ! D2 $end
$var wire 1 " C2 $end
$var wire 1 # B2 $end
$var wire 1 $ A2 $end
$scope module S1 $end
$var wire 1 , R $end
$var wire 1 0 S $end
$var wire 1 ) c $end
$var wire 1 * clk $end
$var wire 1 + p $end
$var wire 1 8 b $end
$var wire 1 9 a $end
$var wire 1 7 Qb $end
$var wire 1 $ Q $end
$scope module S1 $end
$var wire 1 9 Q $end
$var wire 1 8 Qb $end
$var wire 1 , R $end
$var wire 1 0 S $end
$var wire 1 ) c $end
$var wire 1 : clk $end
$var wire 1 + p $end
$var wire 1 ; rk $end
$var wire 1 < sk $end
$upscope $end
$scope module S2 $end
$var wire 1 $ Q $end
$var wire 1 7 Qb $end
$var wire 1 8 R $end
$var wire 1 9 S $end
$var wire 1 ) c $end
$var wire 1 * clk $end
$var wire 1 + p $end
$var wire 1 = rk $end
$var wire 1 > sk $end
$upscope $end
$upscope $end
$scope module S2 $end
$var wire 1 - R $end
$var wire 1 1 S $end
$var wire 1 ) c $end
$var wire 1 * clk $end
$var wire 1 + p $end
$var wire 1 ? b $end
$var wire 1 @ a $end
$var wire 1 6 Qb $end
$var wire 1 # Q $end
$scope module S1 $end
$var wire 1 @ Q $end
$var wire 1 ? Qb $end
$var wire 1 - R $end
$var wire 1 1 S $end
$var wire 1 ) c $end
$var wire 1 A clk $end
$var wire 1 + p $end
$var wire 1 B rk $end
$var wire 1 C sk $end
$upscope $end
$scope module S2 $end
$var wire 1 # Q $end
$var wire 1 6 Qb $end
$var wire 1 ? R $end
$var wire 1 @ S $end
$var wire 1 ) c $end
$var wire 1 * clk $end
$var wire 1 + p $end
$var wire 1 D rk $end
$var wire 1 E sk $end
$upscope $end
$upscope $end
$scope module S3 $end
$var wire 1 . R $end
$var wire 1 2 S $end
$var wire 1 ) c $end
$var wire 1 * clk $end
$var wire 1 + p $end
$var wire 1 F b $end
$var wire 1 G a $end
$var wire 1 5 Qb $end
$var wire 1 " Q $end
$scope module S1 $end
$var wire 1 G Q $end
$var wire 1 F Qb $end
$var wire 1 . R $end
$var wire 1 2 S $end
$var wire 1 ) c $end
$var wire 1 H clk $end
$var wire 1 + p $end
$var wire 1 I rk $end
$var wire 1 J sk $end
$upscope $end
$scope module S2 $end
$var wire 1 " Q $end
$var wire 1 5 Qb $end
$var wire 1 F R $end
$var wire 1 G S $end
$var wire 1 ) c $end
$var wire 1 * clk $end
$var wire 1 + p $end
$var wire 1 K rk $end
$var wire 1 L sk $end
$upscope $end
$upscope $end
$scope module S4 $end
$var wire 1 / R $end
$var wire 1 3 S $end
$var wire 1 ) c $end
$var wire 1 * clk $end
$var wire 1 + p $end
$var wire 1 M b $end
$var wire 1 N a $end
$var wire 1 4 Qb $end
$var wire 1 ! Q $end
$scope module S1 $end
$var wire 1 N Q $end
$var wire 1 M Qb $end
$var wire 1 / R $end
$var wire 1 3 S $end
$var wire 1 ) c $end
$var wire 1 O clk $end
$var wire 1 + p $end
$var wire 1 P rk $end
$var wire 1 Q sk $end
$upscope $end
$scope module S2 $end
$var wire 1 ! Q $end
$var wire 1 4 Qb $end
$var wire 1 M R $end
$var wire 1 N S $end
$var wire 1 ) c $end
$var wire 1 * clk $end
$var wire 1 + p $end
$var wire 1 R rk $end
$var wire 1 S sk $end
$upscope $end
$upscope $end
$upscope $end
$upscope $end
$enddefinitions $end
#0
$dumpvars
1S
1R
0Q
1P
1O
1N
1M
1L
1K
1J
1I
1H
0G
1F
1E
1D
1C
1B
1A
0@
1?
1>
1=
1<
0;
1:
09
18
17
16
15
14
13
02
01
00
0/
0.
0-
1,
0+
0*
1)
0(
0'
0&
0%
0$
0#
0"
0!
$end
#1
0M
0)
#5
04
1!
1;
1Q
0:
0=
0A
0D
0H
0K
0O
0S
1*
#6
12
0,
1(
#10
0F
1G
0J
0Q
1:
1=
1A
1D
1H
1K
1O
1S
0*
#15
05
1"
1J
1Q
0:
0=
0A
0D
0H
0L
0O
0S
1*
#16
1/
03
1'
#20
0N
1M
0J
0P
1:
1=
1A
1D
1H
1L
1O
1S
0*
#25
0!
14
1J
1P
0:
0=
0A
0D
0H
0L
0O
0R
1*
#26
02
11
0(
#30
0?
1@
0C
0P
1:
1=
1A
1D
1H
1L
1O
1R
0*
#35
06
1#
1C
1P
0:
0=
0A
0E
0H
0L
0O
0R
1*
#36
0/
13
1&
#40
0M
1N
0C
0Q
1:
1=
1A
1E
1H
1L
1O
1R
0*
#45
04
1!
1C
1Q
0:
0=
0A
0E
0H
0L
0O
0S
1*
#46
1.
01
1(
#50
0G
1F
0I
0Q
1:
1=
1A
1E
1H
1L
1O
1S
0*
#55
0"
15
1I
1Q
0:
0=
0A
0E
0H
0K
0O
0S
1*
#56
03
1/
0'
#60
0N
1M
0I
0P
1:
1=
1A
1E
1H
1K
1O
1S
0*
#65
0!
14
1I
1P
0:
0=
0A
0E
0H
0K
0O
0R
1*
#66
0.
10
0(
#70
08
19
0<
0P
1:
1=
1A
1E
1H
1K
1O
1R
0*
#75
07
1$
1<
1P
0:
0>
0A
0E
0H
0K
0O
0R
1*
#76
13
0/
1%
#80
0M
1N
0<
0Q
1:
1>
1A
1E
1H
1K
1O
1R
0*
#85
04
1!
1<
1Q
0:
0>
0A
0E
0H
0K
0O
0S
1*
#86
12
00
1(
#90
0F
1G
0J
0Q
1:
1>
1A
1E
1H
1K
1O
1S
0*
#95
05
1"
1J
1Q
0:
0>
0A
0E
0H
0L
0O
0S
1*
#96
1/
03
1'
#100
0N
1M
0J
0P
1:
1>
1A
1E
1H
1L
1O
1S
0*
#105
0!
14
1J
1P
0:
0>
0A
0E
0H
0L
0O
0R
1*
#106
02
1-
0(
#110
0@
1?
0B
0P
1:
1>
1A
1E
1H
1L
1O
1R
0*
#115
0#
16
1B
1P
0:
0>
0A
0D
0H
0L
0O
0R
1*
#116
0/
13
0&
#120
0M
1N
0B
0Q
1:
1>
1A
1D
1H
1L
1O
1R
0*
#125
04
1!
1B
1Q
0:
0>
0A
0D
0H
0L
0O
0S
1*
#126
1.
0-
1(
#130
0G
1F
0I
0Q
1:
1>
1A
1D
1H
1L
1O
1S
0*
#135
0"
15
1I
1Q
0:
0>
0A
0D
0H
0K
0O
0S
1*
#136
03
1/
0'
#140
0N
1M
0I
0P
1:
1>
1A
1D
1H
1K
1O
1S
0*
#145
0!
14
1I
1P
0:
0>
0A
0D
0H
0K
0O
0R
1*
#146
0.
1,
0(
#150
09
18
0;
0P
1:
1>
1A
1D
1H
1K
1O
1R
0*
#155
0$
17
1;
1P
0:
0=
0A
0D
0H
0K
0O
0R
1*
#156
13
0/
0%
#160
0M
1N
0;
0Q
1:
1=
1A
1D
1H
1K
1O
1R
0*
#165
04
1!
1;
1Q
0:
0=
0A
0D
0H
0K
0O
0S
1*
#166
12
0,
1(
#170
0F
1G
0J
0Q
1:
1=
1A
1D
1H
1K
1O
1S
0*
#175
05
1"
1J
1Q
0:
0=
0A
0D
0H
0L
0O
0S
1*
#176
1/
03
1'
#180
0N
1M
0J
0P
1:
1=
1A
1D
1H
1L
1O
1S
0*
#185
0!
14
1J
1P
0:
0=
0A
0D
0H
0L
0O
0R
1*
#186
02
11
0(
#190
0?
1@
0C
0P
1:
1=
1A
1D
1H
1L
1O
1R
0*
#195
06
1#
1C
1P
0:
0=
0A
0E
0H
0L
0O
0R
1*
#196
0/
13
1&
#200
0M
1N
0C
0Q
1:
1=
1A
1E
1H
1L
1O
1R
0*
#205
04
1!
1C
1Q
0:
0=
0A
0E
0H
0L
0O
0S
1*
#206
1.
01
1(
#210
0G
1F
0I
0Q
1:
1=
1A
1E
1H
1L
1O
1S
0*
#215
0"
15
1I
1Q
0:
0=
0A
0E
0H
0K
0O
0S
1*
#216
03
1/
0'
#220
0N
1M
0I
0P
1:
1=
1A
1E
1H
1K
1O
1S
0*
#225
0!
14
1I
1P
0:
0=
0A
0E
0H
0K
0O
0R
1*
#226
0.
10
0(
#230
08
19
0<
0P
1:
1=
1A
1E
1H
1K
1O
1R
0*
#235
07
1$
1<
1P
0:
0>
0A
0E
0H
0K
0O
0R
1*
#236
13
0/
1%
#240
0M
1N
0<
0Q
1:
1>
1A
1E
1H
1K
1O
1R
0*
#245
04
1!
1<
1Q
0:
0>
0A
0E
0H
0K
0O
0S
1*
#246
12
00
1(
#250
0F
1G
0J
0Q
1:
1>
1A
1E
1H
1K
1O
1S
0*
#255
05
1"
1J
1Q
0:
0>
0A
0E
0H
0L
0O
0S
1*
#256
1/
03
1'
#260
0N
1M
0J
0P
1:
1>
1A
1E
1H
1L
1O
1S
0*
#265
0!
14
1J
1P
0:
0>
0A
0E
0H
0L
0O
0R
1*
#266
02
1-
0(
#270
0@
1?
0B
0P
1:
1>
1A
1E
1H
1L
1O
1R
0*
#275
0#
16
1B
1P
0:
0>
0A
0D
0H
0L
0O
0R
1*
#276
0/
13
0&
#280
0M
1N
0B
0Q
1:
1>
1A
1D
1H
1L
1O
1R
0*
#285
04
1!
1B
1Q
0:
0>
0A
0D
0H
0L
0O
0S
1*
#286
1.
0-
1(
#290
0G
1F
0I
0Q
1:
1>
1A
1D
1H
1L
1O
1S
0*
#295
0"
15
1I
1Q
0:
0>
0A
0D
0H
0K
0O
0S
1*
#296
03
1/
0'
#300
0N
1M
0I
0P
1:
1>
1A
1D
1H
1K
1O
1S
0*
#305
0!
14
1I
1P
0:
0>
0A
0D
0H
0K
0O
0R
1*
#306
0.
1,
0(
#310
09
18
0;
0P
1:
1>
1A
1D
1H
1K
1O
1R
0*
#315
0$
17
1;
1P
0:
0=
0A
0D
0H
0K
0O
0R
1*
#316
13
0/
0%
#320
0M
1N
0;
0Q
1:
1=
1A
1D
1H
1K
1O
1R
0*
#325
04
1!
1;
1Q
0:
0=
0A
0D
0H
0K
0O
0S
1*
#326
12
0,
1(
#330
0F
1G
0J
0Q
1:
1=
1A
1D
1H
1K
1O
1S
0*
#335
05
1"
1J
1Q
0:
0=
0A
0D
0H
0L
0O
0S
1*
#336
1/
03
1'
#340
0N
1M
0J
0P
1:
1=
1A
1D
1H
1L
1O
1S
0*
#345
0!
14
1J
1P
0:
0=
0A
0D
0H
0L
0O
0R
1*
#346
02
11
0(
#350
0?
1@
0C
0P
1:
1=
1A
1D
1H
1L
1O
1R
0*
#355
06
1#
1C
1P
0:
0=
0A
0E
0H
0L
0O
0R
1*
#356
0/
13
1&
#360
0M
1N
0C
0Q
1:
1=
1A
1E
1H
1L
1O
1R
0*
#365
04
1!
1C
1Q
0:
0=
0A
0E
0H
0L
0O
0S
1*
#366
1.
01
1(
#370
0G
1F
0I
0Q
1:
1=
1A
1E
1H
1L
1O
1S
0*
#375
0"
15
1I
1Q
0:
0=
0A
0E
0H
0K
0O
0S
1*
#376
03
1/
0'
#380
0N
1M
0I
0P
1:
1=
1A
1E
1H
1K
1O
1S
0*
#385
0!
14
1I
1P
0:
0=
0A
0E
0H
0K
0O
0R
1*
#386
0.
10
0(
#390
08
19
0<
0P
1:
1=
1A
1E
1H
1K
1O
1R
0*
#395
07
1$
1<
1P
0:
0>
0A
0E
0H
0K
0O
0R
1*
#396
13
0/
1%
#400
0M
1N
0<
0Q
1:
1>
1A
1E
1H
1K
1O
1R
0*
#405
04
1!
1<
1Q
0:
0>
0A
0E
0H
0K
0O
0S
1*
#406
12
00
1(
#410
0F
1G
0J
0Q
1:
1>
1A
1E
1H
1K
1O
1S
0*
#415
05
1"
1J
1Q
0:
0>
0A
0E
0H
0L
0O
0S
1*
#416
1/
03
1'
#420
0N
1M
0J
0P
1:
1>
1A
1E
1H
1L
1O
1S
0*
#425
0!
14
1J
1P
0:
0>
0A
0E
0H
0L
0O
0R
1*
#426
02
1-
0(
#430
0@
1?
0B
0P
1:
1>
1A
1E
1H
1L
1O
1R
0*
#435
0#
16
1B
1P
0:
0>
0A
0D
0H
0L
0O
0R
1*
#436
0/
13
0&
#440
0M
1N
0B
0Q
1:
1>
1A
1D
1H
1L
1O
1R
0*
#445
04
1!
1B
1Q
0:
0>
0A
0D
0H
0L
0O
0S
1*
#446
1.
0-
1(
#450
0G
1F
0I
0Q
1:
1>
1A
1D
1H
1L
1O
1S
0*
#455
0"
15
1I
1Q
0:
0>
0A
0D
0H
0K
0O
0S
1*
#456
03
1/
0'
#460
0N
1M
0I
0P
1:
1>
1A
1D
1H
1K
1O
1S
0*
#465
0!
14
1I
1P
0:
0>
0A
0D
0H
0K
0O
0R
1*
#466
0.
1,
0(
#470
09
18
0;
0P
1:
1>
1A
1D
1H
1K
1O
1R
0*
#475
0$
17
1;
1P
0:
0=
0A
0D
0H
0K
0O
0R
1*
#476
13
0/
0%
#480
0M
1N
0;
0Q
1:
1=
1A
1D
1H
1K
1O
1R
0*
#485
04
1!
1;
1Q
0:
0=
0A
0D
0H
0K
0O
0S
1*
#486
12
0,
1(
#490
0F
1G
0J
0Q
1:
1=
1A
1D
1H
1K
1O
1S
0*
#495
05
1"
1J
1Q
0:
0=
0A
0D
0H
0L
0O
0S
1*
#496
1/
03
1'
#500
0N
1M
0J
0P
1:
1=
1A
1D
1H
1L
1O
1S
0*
